{
    "name": "PSPNet",
    "n_gpu": 4,
    "use_synch_bn": true,

    "arch": {
        "type": "PSPNet",
        "args": {
            "backbone": "resnet50",
            "freeze_bn": false,
            "freeze_backbone": false
        }
    },

    "train_loader": {
        "type": "VOC",
        "args":{
            "data_dir": "VOC2012",
            "batch_size": 2,
            "base_size": 512,
            "crop_size": 473,
            "augment": true,
            "shuffle": true,
            "scale": true,
            "flip": true,
            "rotate": true,
            "blur": false,
			"noise": true,
            "split": "train_aug",
            "num_workers": 8
        }
    },

    "val_loader": {
        "type": "VOC",
        "args":{
            "data_dir": "VOC2012",
            "batch_size": 16,
	    "base_size": 512,
            "crop_size": 473,
            "val": true,
            "split": "val",
            "num_workers": 6
        }
    },

    "optimizer": {
        "type": "SGD",
        "differential_lr": true,
        "args":{
            "lr": 0.02,
            "weight_decay": 1e-4,
            "momentum": 0.9
        }
    },

    "loss": "CrossEntropyLoss2d",
    "ignore_index": 255,
    "lr_scheduler": {
        "type": "Poly",
        "args": {}
    },

    "trainer": {
        "epochs": 80,
        "save_dir": "saved/",
        "save_period": 3,
  
        "monitor": "max Mean_IoU",
        "early_stop": 10,
        
        "tensorboard": true,
        "log_dir": "saved/runs",
        "log_per_iter": 100,

        "val": true,
        "val_per_epochs": 3
    }
}
